{
  "latest": "0.0.79",
  "platforms": {
    "linux-x64": {
      "version": "0.0.79",
      "url": "https://drive.nubem.org/downloads/Nubem-Drive-0.0.79-amd64.deb",
      "fileName": "Nubem-Drive-0.0.79-amd64.deb",
      "sha256": "4e4fe3c3112870c205789771f995a51afc9bd388b42ed60045831fa149d45deb",
      "type": "deb"
    },
    "linux-x64-server": {
      "version": "0.0.79",
      "url": "https://drive.nubem.org/downloads/Nubem-Server-0.0.79-amd64.deb",
      "fileName": "Nubem-Server-0.0.79-amd64.deb",
      "sha256": "7f4d743e31f04ec69f078d89d25e3ac647455c217747c5553b099ab4bd6df362",
      "type": "deb"
    },
    "win32-x64": {
      "version": "0.0.75",
      "url": "https://drive.nubem.org/downloads/Nubem-Drive-Setup-0.0.75-x64.exe",
      "fileName": "Nubem-Drive-Setup-0.0.75-x64.exe",
      "sha256": "01034561afd99c14789a46f7619358eef6561de1d6824daaae4d2329d6a85462",
      "type": "nsis"
    }
  }
}
